{
  "timezone": "Europe/London",
  "holidays": {
    "10/12/2021":"Our Lady of Aparecida's day",
    "11/02/2021":"All Souls Day",
    "11/15/2021":"Republic Day",
    "12/25/2021":"Christmas Day",
    "01/01/2022":"New Year's Day",
    "02/16/2022":"Shrove Tuesday",
    "04/02/2022":"Good Friday",
    "04/04/2022":"Easter Sunday",
    "04/21/2022":"Tiradentes Day",
    "05/01/2022":"Labour Day",
    "06/03/2022":"Corpus Christi",
    "09/07/2022":"Independence Day",
    "10/12/2022":"Our Lady of Aparecida's day"
  },
  "operatingHours": {
    "webchat": {
      "1": [{ "open": 0000, "close": 2359 }],
      "2": [{ "open": 0000, "close": 2359 }],
      "3": [{ "open": 0000, "close": 2359 }],
      "4": [{ "open": 0000, "close": 2359 }],
      "5": [{ "open": 0000, "close": 2359 }],
      "6": [{ "open": 0000, "close": 2359 }],
      "7": [{ "open": 0000, "close": 2359 }]
    }
  }
}
